pyninaapiio
