Metadata-Version: 2.4
Name: pyninaapiio
Version: 0.2.2.13.7
Summary: Python Wrapper for N.I.N.A. Advanced API
Home-page: https://github.com/mawinkler/pyninaapiio
Author: Markus Winkler
Author-email: winkler.info@icloud.com
License: MIT
Keywords: N.I.N.A.,NinaAPI,Python
Classifier: Development Status :: 4 - Beta
Classifier: Intended Audience :: Developers
Classifier: Topic :: Software Development :: Build Tools
Classifier: License :: OSI Approved :: MIT License
Classifier: Programming Language :: Python :: 3
Classifier: Programming Language :: Python :: 3.6
Classifier: Programming Language :: Python :: 3.7
Classifier: Programming Language :: Python :: 3.8
Classifier: Programming Language :: Python :: 3.9
Classifier: Programming Language :: Python :: 3.10
Classifier: Programming Language :: Python :: 3.11
Classifier: Programming Language :: Python :: 3.12
Classifier: Programming Language :: Python :: 3.13
License-File: LICENSE
Requires-Dist: httpx
Requires-Dist: attrs
Requires-Dist: typeguard
Dynamic: author
Dynamic: author-email
Dynamic: classifier
Dynamic: description
Dynamic: home-page
Dynamic: keywords
Dynamic: license
Dynamic: license-file
Dynamic: requires-dist
Dynamic: summary
